glibc.py
glibc-0.6.1.dist-info/zip-safe
glibc-0.6.1.dist-info/WHEEL
glibc-0.6.1.dist-info/top_level.txt
glibc-0.6.1.dist-info/metadata.json
glibc-0.6.1.dist-info/RECORD
glibc-0.6.1.dist-info/METADATA
glibc-0.6.1.dist-info/DESCRIPTION.rst
pyglibc/selectors.py
pyglibc/__init__.py
pyglibc/_signalfd.py
pyglibc/_subreaper.py
pyglibc/select.py
pyglibc/_pthread_sigmask.py
pyglibc/_abc.py
pyglibc/_pipe.py
