Metadata-Version: 1.1
Name: glibc
Version: 0.6.1
Summary: Pure-Python bindings to glibc (based on ctypes)
Home-page: https://github.com/zyga/python-glibc/
Author: Zygmunt Krynicki
Author-email: zygmunt.krynicki@canonical.com
License: LGPLv3
Platform: Linux
Classifier: Development Status :: 5 - Production/Stable
Classifier: Intended Audience :: Developers
Classifier: License :: OSI Approved :: GNU Lesser General Public License v3 (LGPLv3)
Classifier: Natural Language :: English
Classifier: Operating System :: POSIX :: Linux
Classifier: Programming Language :: Python :: 2.7
Classifier: Programming Language :: Python :: 3.2
Classifier: Programming Language :: Python :: 3.3
Classifier: Programming Language :: Python :: 3.4
Classifier: Programming Language :: Python :: Implementation :: CPython
Classifier: Programming Language :: Python :: Implementation :: PyPy
Classifier: Topic :: Software Development :: Libraries :: Python Modules
